setup.cfg
setup.py
credentials/__init__.py
credentials/backends.py
credentials/base.py
credentials_sauce.egg-info/PKG-INFO
credentials_sauce.egg-info/SOURCES.txt
credentials_sauce.egg-info/dependency_links.txt
credentials_sauce.egg-info/top_level.txt