Metadata-Version: 1.0
Name: credentials-sauce
Version: 1.2
Summary: Credential Manager
Home-page: https://github.com/OniOni/credentials
Author: Mathieu Sabourin
Author-email: mathieu.c.sabourin@gmail.com
License: LGPLv3
Platform: UNKNOWN
